{"data":[{"release_key":"221005","address_id":"item_coin_00000020","address_type":"","path":"item_coin_00000020"},{"release_key":"221005","address_id":"item_medal_00000031","address_type":"","path":"item_medal_00000031"},{"release_key":"221005","address_id":"item_medal_00000032","address_type":"","path":"item_medal_00000032"},{"release_key":"221005","address_id":"item_medal_00000033","address_type":"","path":"item_medal_00000033"},{"release_key":"221005","address_id":"item_medal_00000035","address_type":"","path":"item_medal_00000035"},{"release_key":"221005","address_id":"item_medal_00000036","address_type":"","path":"item_medal_00000036"},{"release_key":"221005","address_id":"item_medal_00000037","address_type":"","path":"item_medal_00000037"},{"release_key":"221005","address_id":"item_medal_00000038","address_type":"","path":"item_medal_00000038"},{"release_key":"221005","address_id":"item_medal_00000039","address_type":"","path":"item_medal_00000039"},{"release_key":"221203","address_id":"item_medal_00000045","address_type":"","path":"item_medal_00000045"},{"release_key":"230702","address_id":"item_ticket_04200006","address_type":"","path":"item_ticket_04200006"},{"release_key":"230901","address_id":"item_ticket_04200007","address_type":"","path":"item_ticket_04200007"},{"release_key":"221005","address_id":"item_ticket_04400001","address_type":"","path":"item_ticket_04400001"},{"release_key":"221005","address_id":"item_ticket_04500002","address_type":"","path":"item_ticket_04500002"},{"release_key":"221104","address_id":"item_ticket_04500003","address_type":"","path":"item_ticket_04500003"},{"release_key":"221201","address_id":"item_ticket_04500004","address_type":"","path":"item_ticket_04500004"},{"release_key":"221203","address_id":"item_ticket_04500006","address_type":"","path":"item_ticket_04500006"},{"release_key":"230101","address_id":"item_ticket_04500007","address_type":"","path":"item_ticket_04500007"},{"release_key":"230301","address_id":"item_ticket_04500009","address_type":"","path":"item_ticket_04500009"},{"release_key":"230401","address_id":"item_ticket_04500010","address_type":"","path":"item_ticket_04500010"},{"release_key":"230402","address_id":"item_ticket_04500011","address_type":"","path":"item_ticket_04500011"},{"release_key":"230501","address_id":"item_ticket_04500012","address_type":"","path":"item_ticket_04500012"},{"release_key":"230501","address_id":"item_ticket_04500013","address_type":"","path":"item_ticket_04500013"},{"release_key":"230502","address_id":"item_ticket_04500014","address_type":"","path":"item_ticket_04500014"},{"release_key":"230502","address_id":"item_ticket_04500015","address_type":"","path":"item_ticket_04500015"},{"release_key":"230601","address_id":"item_ticket_04500016","address_type":"","path":"item_ticket_04500016"},{"release_key":"230602","address_id":"item_ticket_04500017","address_type":"","path":"item_ticket_04500017"},{"release_key":"230701","address_id":"item_ticket_04500018","address_type":"","path":"item_ticket_04500018"},{"release_key":"230701","address_id":"item_ticket_04500023","address_type":"","path":"item_ticket_04500023"},{"release_key":"230702","address_id":"item_ticket_04500026","address_type":"","path":"item_ticket_04500026"},{"release_key":"230801","address_id":"item_ticket_04500028","address_type":"","path":"item_ticket_04500028"},{"release_key":"230802","address_id":"item_ticket_04500029","address_type":"","path":"item_ticket_04500029"},{"release_key":"230901","address_id":"item_ticket_04500030","address_type":"","path":"item_ticket_04500030"},{"release_key":"230901","address_id":"item_ticket_04500031","address_type":"","path":"item_ticket_04500031"},{"release_key":"230901","address_id":"item_ticket_04500032","address_type":"","path":"item_ticket_04500032"},{"release_key":"230901","address_id":"item_ticket_04500033","address_type":"","path":"item_ticket_04500033"},{"release_key":"230901","address_id":"item_ticket_04500034","address_type":"","path":"item_ticket_04500034"}]}