{"data":[{"release_key":"220201","filter_sort_id":10101,"target":"equip","category":"filter","type":"rare","column":"1"},{"release_key":"220201","filter_sort_id":10102,"target":"equip","category":"filter","type":"rare","column":"2"},{"release_key":"220201","filter_sort_id":10103,"target":"equip","category":"filter","type":"rare","column":"3"},{"release_key":"220201","filter_sort_id":10104,"target":"equip","category":"filter","type":"rare","column":"4"},{"release_key":"220201","filter_sort_id":10105,"target":"equip","category":"filter","type":"rare","column":"5"},{"release_key":"220201","filter_sort_id":10201,"target":"equip","category":"filter","type":"limitbreak","column":"0"},{"release_key":"220201","filter_sort_id":10202,"target":"equip","category":"filter","type":"limitbreak","column":"1"},{"release_key":"220201","filter_sort_id":10203,"target":"equip","category":"filter","type":"limitbreak","column":"2"},{"release_key":"220201","filter_sort_id":10204,"target":"equip","category":"filter","type":"limitbreak","column":"3"},{"release_key":"220201","filter_sort_id":10205,"target":"equip","category":"filter","type":"limitbreak","column":"4"},{"release_key":"220201","filter_sort_id":10301,"target":"equip","category":"filter","type":"param","column":"hp","skill_effect_id":"buff_add_hp_heal"},{"release_key":"220201","filter_sort_id":10302,"target":"equip","category":"filter","type":"param","column":"atk","skill_effect_id":"buff_add_atk"},{"release_key":"220201","filter_sort_id":10303,"target":"equip","category":"filter","type":"param","column":"matk","skill_effect_id":"buff_add_matk"},{"release_key":"220201","filter_sort_id":10304,"target":"equip","category":"filter","type":"param","column":"def","skill_effect_id":"buff_add_def"},{"release_key":"220201","filter_sort_id":10305,"target":"equip","category":"filter","type":"param","column":"mdef","skill_effect_id":"buff_add_mdef"},{"release_key":"220201","filter_sort_id":10401,"target":"equip","category":"filter","type":"abnormal_res","column":"bind","skill_effect_id":"STATE_RESIST_BIND"},{"release_key":"220201","filter_sort_id":10403,"target":"equip","category":"filter","type":"abnormal_res","column":"bind_skill","skill_effect_id":"STATE_RESIST_BIND_SKILL"},{"release_key":"220201","filter_sort_id":10501,"target":"equip","category":"filter","type":"abnormal_dmg_res","column":"flame","skill_effect_id":"protect_add_state_burn"},{"release_key":"220201","filter_sort_id":10503,"target":"equip","category":"filter","type":"abnormal_dmg_res","column":"bomb","skill_effect_id":"protect_add_state_bomb"},{"release_key":"220201","filter_sort_id":10504,"target":"equip","category":"filter","type":"abnormal_dmg_res","column":"nightmare","skill_effect_id":"protect_add_state_nightmare"},{"release_key":"220201","filter_sort_id":10601,"target":"equip","category":"filter","type":"color_killer","column":"red","skill_effect_id":"killer_add_color_red"},{"release_key":"220201","filter_sort_id":10602,"target":"equip","category":"filter","type":"color_killer","column":"green","skill_effect_id":"killer_add_color_green"},{"release_key":"220201","filter_sort_id":10603,"target":"equip","category":"filter","type":"color_killer","column":"yellow","skill_effect_id":"killer_add_color_yellow"},{"release_key":"220201","filter_sort_id":10604,"target":"equip","category":"filter","type":"color_killer","column":"blue","skill_effect_id":"killer_add_color_blue"},{"release_key":"220201","filter_sort_id":10605,"target":"equip","category":"filter","type":"color_killer","column":"white","skill_effect_id":"killer_add_color_white"},{"release_key":"220201","filter_sort_id":10606,"target":"equip","category":"filter","type":"color_killer","column":"black","skill_effect_id":"killer_add_color_black"},{"release_key":"220201","filter_sort_id":10701,"target":"equip","category":"filter","type":"type_killer","column":"dealer","skill_effect_id":"killer_add_type_dealer"},{"release_key":"220201","filter_sort_id":10702,"target":"equip","category":"filter","type":"type_killer","column":"buffer","skill_effect_id":"killer_add_type_buffer"},{"release_key":"220201","filter_sort_id":10703,"target":"equip","category":"filter","type":"type_killer","column":"debuffer","skill_effect_id":"killer_add_type_debuffer"},{"release_key":"220201","filter_sort_id":10704,"target":"equip","category":"filter","type":"type_killer","column":"tanker","skill_effect_id":"killer_add_type_tanker"},{"release_key":"220201","filter_sort_id":10705,"target":"equip","category":"filter","type":"type_killer","column":"healer","skill_effect_id":"killer_add_type_healer"},{"release_key":"220201","filter_sort_id":10801,"target":"equip","category":"filter","type":"color_dmg_res","column":"red","skill_effect_id":"protect_add_color_red"},{"release_key":"220201","filter_sort_id":10802,"target":"equip","category":"filter","type":"color_dmg_res","column":"green","skill_effect_id":"protect_add_color_green"},{"release_key":"220201","filter_sort_id":10803,"target":"equip","category":"filter","type":"color_dmg_res","column":"yellow","skill_effect_id":"protect_add_color_yellow"},{"release_key":"220201","filter_sort_id":10804,"target":"equip","category":"filter","type":"color_dmg_res","column":"blue","skill_effect_id":"protect_add_color_blue"},{"release_key":"220201","filter_sort_id":10805,"target":"equip","category":"filter","type":"color_dmg_res","column":"white","skill_effect_id":"protect_add_color_white"},{"release_key":"220201","filter_sort_id":10806,"target":"equip","category":"filter","type":"color_dmg_res","column":"black","skill_effect_id":"protect_add_color_black"},{"release_key":"220201","filter_sort_id":10901,"target":"equip","category":"filter","type":"type_dmg_res","column":"dealer","skill_effect_id":"protect_add_type_dealer"},{"release_key":"220201","filter_sort_id":10902,"target":"equip","category":"filter","type":"type_dmg_res","column":"buffer","skill_effect_id":"protect_add_type_buffer"},{"release_key":"220201","filter_sort_id":10903,"target":"equip","category":"filter","type":"type_dmg_res","column":"debuffer","skill_effect_id":"protect_add_type_debuffer"},{"release_key":"220201","filter_sort_id":10904,"target":"equip","category":"filter","type":"type_dmg_res","column":"tanker","skill_effect_id":"protect_add_type_tanker"},{"release_key":"220201","filter_sort_id":10905,"target":"equip","category":"filter","type":"type_dmg_res","column":"healer","skill_effect_id":"protect_add_type_healer"},{"release_key":"220201","filter_sort_id":11201,"target":"equip","category":"filter","type":"armor","column":"bind","skill_effect_id":"armor_add_state_bind"},{"release_key":"220201","filter_sort_id":11203,"target":"equip","category":"filter","type":"armor","column":"bind_skill","skill_effect_id":"armor_add_state_bind_skill"},{"release_key":"220201","filter_sort_id":11204,"target":"equip","category":"filter","type":"armor","column":"virus","skill_effect_id":"armor_add_state_virus"},{"release_key":"220201","filter_sort_id":11205,"target":"equip","category":"filter","type":"armor","column":"flame","skill_effect_id":"armor_add_state_burn"},{"release_key":"220201","filter_sort_id":11301,"target":"equip","category":"filter","type":"others","column":"extend_operation","skill_effect_id":"operation_time_extend"},{"release_key":"220201","filter_sort_id":20101,"target":"equip","category":"sort","type":"common","column":"rare"},{"release_key":"220201","filter_sort_id":20102,"target":"equip","category":"sort","type":"common","column":"cost"},{"release_key":"220201","filter_sort_id":20103,"target":"equip","category":"sort","type":"common","column":"lv"},{"release_key":"220201","filter_sort_id":20104,"target":"equip","category":"sort","type":"common","column":"limitbreak"},{"release_key":"220201","filter_sort_id":20201,"target":"equip","category":"sort","type":"status","column":"hp"},{"release_key":"220201","filter_sort_id":20202,"target":"equip","category":"sort","type":"status","column":"atk"},{"release_key":"220201","filter_sort_id":20203,"target":"equip","category":"sort","type":"status","column":"matk"},{"release_key":"220201","filter_sort_id":20204,"target":"equip","category":"sort","type":"status","column":"def"},{"release_key":"220201","filter_sort_id":20205,"target":"equip","category":"sort","type":"status","column":"mdef"},{"release_key":"220201","filter_sort_id":20301,"target":"equip","category":"sort","type":"others","column":"entry"},{"release_key":"220201","filter_sort_id":20302,"target":"equip","category":"sort","type":"others","column":"count"},{"release_key":"220201","filter_sort_id":30101,"target":"unit","category":"sort","type":"common","column":"rare"},{"release_key":"220201","filter_sort_id":30102,"target":"unit","category":"sort","type":"common","column":"lv"},{"release_key":"220201","filter_sort_id":30103,"target":"unit","category":"sort","type":"common","column":"rank"},{"release_key":"220201","filter_sort_id":30104,"target":"unit","category":"sort","type":"common","column":"intimacy"},{"release_key":"220201","filter_sort_id":30105,"target":"unit","category":"sort","type":"common","column":"atk_matk"},{"release_key":"220201","filter_sort_id":30106,"target":"unit","category":"sort","type":"common","column":"type"},{"release_key":"220201","filter_sort_id":30201,"target":"unit","category":"sort","type":"status","column":"total"},{"release_key":"220201","filter_sort_id":30202,"target":"unit","category":"sort","type":"status","column":"hp"},{"release_key":"220201","filter_sort_id":30203,"target":"unit","category":"sort","type":"status","column":"atk"},{"release_key":"220201","filter_sort_id":30204,"target":"unit","category":"sort","type":"status","column":"matk"},{"release_key":"220201","filter_sort_id":30205,"target":"unit","category":"sort","type":"status","column":"def"},{"release_key":"220201","filter_sort_id":30206,"target":"unit","category":"sort","type":"status","column":"mdef"},{"release_key":"220201","filter_sort_id":30207,"target":"unit","category":"sort","type":"status","column":"cri_rate"},{"release_key":"220201","filter_sort_id":30208,"target":"unit","category":"sort","type":"status","column":"cri_res"},{"release_key":"220201","filter_sort_id":30209,"target":"unit","category":"sort","type":"status","column":"cri_dmg"},{"release_key":"220201","filter_sort_id":30210,"target":"unit","category":"sort","type":"status","column":"hp_drain"},{"release_key":"220201","filter_sort_id":30211,"target":"unit","category":"sort","type":"status","column":"dmg_reflect"},{"release_key":"220201","filter_sort_id":30212,"target":"unit","category":"sort","type":"status","column":"hp_heal"},{"release_key":"220201","filter_sort_id":30213,"target":"unit","category":"sort","type":"status","column":"abnormal_res"}]}